dfgen/__init__.py
dfgen/dockerfile.py
dfgen/file_actions.py
dfgen/scripts/build.sh
dfgen/templates/__init__.py
dfgen/templates/docker/Dockerfile.jinja2
dfgen/templates/docker/__init__.py
dfgen/templates/docker/apk.jinja2
dfgen/templates/docker/apt-get.jinja2
dfgen-0.2.data/scripts/dfgen
dfgen-0.2.dist-info/LICENSE.txt
dfgen-0.2.dist-info/METADATA
dfgen-0.2.dist-info/WHEEL
dfgen-0.2.dist-info/top_level.txt
dfgen-0.2.dist-info/RECORD
