Metadata-Version: 2.1
Name: dfgen
Version: 0.2
Summary: A little tool to generate commonly used ci/cd templates like Dockerfiles.
Home-page: https://github.com/merlijntishauser/dfgen
Author: Merlijn Tishauser
Author-email: merlijn@gargleblaster.org
License: UNKNOWN
Download-URL: https://github.com/merlijntishauser/dfgen/archive/v0.1.tar.gz
Keywords: templates,docker,Dockerfile
Platform: UNKNOWN
Requires-Dist: certifi
Requires-Dist: click
Requires-Dist: click-log
Requires-Dist: chardet
Requires-Dist: Jinja2
Requires-Dist: idna
Requires-Dist: MarkupSafe
Requires-Dist: pip
Requires-Dist: requests
Requires-Dist: setuptools
Requires-Dist: urllib3
Requires-Dist: wheel
Provides-Extra: test
Requires-Dist: mock ; extra == 'test'
Requires-Dist: pytest ; extra == 'test'
Requires-Dist: pytest-mock ; extra == 'test'
Requires-Dist: pytest-cov ; extra == 'test'
Requires-Dist: tzlocal ; extra == 'test'
